cvlab/__init__.py
cvlab/main.py
cvlab/setup_project.py
cvlab/autoannotate_utils/__init__.py
cvlab/autoannotate_utils/unsupervised_classification.py
cvlab/gui/__init__.py
cvlab/gui/base.py
cvlab/gui/custom_utils.py
cvlab/gui/dialogs/__init__.py
cvlab/gui/dialogs/export.py
cvlab/gui/dialogs/file_selector.py
cvlab/gui/sections/OLD_auto_annotation.py
cvlab/gui/sections/__init__.py
cvlab/gui/sections/annotation.py
cvlab/gui/sections/data_info.py
cvlab/gui/sections/home.py
cvlab/gui/sections/settings.py
cvlab/gui_data/Roboto-Regular.ttf
cvlab/gui_data/chip.png
cvlab/model/__init__.py
cvlab/model/app.py
cvlab/model/data.py
cvlab/model/project.py
cvlab/utils/__init__.py
cvlab/utils/check_export.py
cvlab/yolov5/.dockerignore
cvlab/yolov5/.gitattributes
cvlab/yolov5/.gitignore
cvlab/yolov5/.pre-commit-config.yaml
cvlab/yolov5/CONTRIBUTING.md
cvlab/yolov5/Dockerfile
cvlab/yolov5/LICENSE
cvlab/yolov5/README.md
cvlab/yolov5/__init__.py
cvlab/yolov5/detect.py
cvlab/yolov5/requirements.txt
cvlab/yolov5/setup.cfg
cvlab/yolov5/data/Argoverse.yaml
cvlab/yolov5/data/GlobalWheat2020.yaml
cvlab/yolov5/data/Objects365.yaml
cvlab/yolov5/data/SKU-110K.yaml
cvlab/yolov5/data/VOC.yaml
cvlab/yolov5/data/VisDrone.yaml
cvlab/yolov5/data/coco.yaml
cvlab/yolov5/data/coco128.yaml
cvlab/yolov5/data/xView.yaml
cvlab/yolov5/data/hyps/hyp.finetune.yaml
cvlab/yolov5/data/hyps/hyp.finetune_objects365.yaml
cvlab/yolov5/data/hyps/hyp.scratch-high.yaml
cvlab/yolov5/data/hyps/hyp.scratch-low.yaml
cvlab/yolov5/data/hyps/hyp.scratch-med.yaml
cvlab/yolov5/data/hyps/hyp.scratch.yaml
cvlab/yolov5/data/images/bus.jpg
cvlab/yolov5/data/images/zidane.jpg
cvlab/yolov5/data/scripts/download_weights.sh
cvlab/yolov5/data/scripts/get_coco.sh
cvlab/yolov5/data/scripts/get_coco128.sh
cvlab/yolov5/models/__init__.py
cvlab/yolov5/models/common.py
cvlab/yolov5/models/experimental.py
cvlab/yolov5/models/yolo.py
cvlab/yolov5/models/yolov5l.yaml
cvlab/yolov5/models/yolov5m.yaml
cvlab/yolov5/models/yolov5n.yaml
cvlab_gui-0.0.36.dist-info/LICENSE
cvlab_gui-0.0.36.dist-info/WHEEL
cvlab_gui-0.0.36.dist-info/METADATA
cvlab_gui-0.0.36.dist-info/RECORD
