Metadata-Version: 2.1
Name: cvlab-gui
Version: 0.0.36
Summary: Object Detection annotation tool entirely written in Python. Automatically annotate entire images using a pretrained object detection model or pseudo-classify single bbounding boxes with Self-Supervised pretrained models.
Author-email: Mauro Sciancalepore <mascit.info@gmail.com>
Requires-Python: >=3.7
Classifier: Intended Audience :: Information Technology
Classifier: Programming Language :: Python :: 3
Classifier: License :: OSI Approved :: MIT License
Classifier: Operating System :: Microsoft :: Windows
Classifier: Operating System :: MacOS
Classifier: Development Status :: 3 - Alpha
Classifier: Topic :: Scientific/Engineering :: Artificial Intelligence
Classifier: Typing :: Typed
Requires-Dist: pyimgui-wheels
Requires-Dist: numpy
Requires-Dist: pandas
Requires-Dist: seaborn
Requires-Dist: faiss-cpu
Requires-Dist: torch
Requires-Dist: torchvision
Requires-Dist: glfw
Requires-Dist: pygame
Requires-Dist: PyYAML
Requires-Dist: tqdm
Requires-Dist: PyOpenGL
Requires-Dist: Pillow
Requires-Dist: imagesize
Requires-Dist: orjson
Requires-Dist: onnx
Requires-Dist: onnxruntime
Requires-Dist: opencv-python-headless<=4.5.3.56
Requires-Dist: stbpy
Requires-Dist: pydantic >=1.6.2,!=1.7,!=1.7.1,!=1.7.2,!=1.7.3,!=1.8,!=1.8.1,<2.0.0
Project-URL: Source, https://github.com/masc-it/CVLAB
